adafruit_mcp4725.py
adafruit_circuitpython_mcp4725-1.4.19.dist-info/licenses/LICENSE
adafruit_circuitpython_mcp4725-1.4.19.dist-info/METADATA
adafruit_circuitpython_mcp4725-1.4.19.dist-info/WHEEL
adafruit_circuitpython_mcp4725-1.4.19.dist-info/top_level.txt
adafruit_circuitpython_mcp4725-1.4.19.dist-info/RECORD
